process_monitor/__init__.py
process_monitor/reader.py
process_monitor/utils.py
process_monitor/monitors/__init__.py
process_monitor/monitors/kinesis_monitor.py
process_monitor/monitors/monitor.py
process_monitor-0.0.1.dist-info/METADATA
process_monitor-0.0.1.dist-info/WHEEL
process_monitor-0.0.1.dist-info/top_level.txt
process_monitor-0.0.1.dist-info/RECORD
