Metadata-Version: 2.1
Name: process-monitor
Version: 0.0.1
Summary: UNKNOWN
Home-page: UNKNOWN
Author: Mohammed Qudah
Author-email: mohghq@gmail.com
License: UNKNOWN
Platform: UNKNOWN
